t1ha/__init__.py
t1ha/backends/__init__.py
t1ha/backends/cffi/__init__.py
t1ha/backends/cffi/_t1ha.pypy39-pp73-darwin.so
t1ha/backends/cffi/build.py
t1ha/backends/cython/__init__.py
t1ha/backends/cython/_t1ha.c
t1ha/backends/cython/_t1ha.pypy39-pp73-darwin.so
t1ha/backends/cython/_t1ha.pyx
t1ha/backends/cython/t1ha.pxd
t1ha-0.1.0.dist-info/METADATA
t1ha-0.1.0.dist-info/WHEEL
t1ha-0.1.0.dist-info/top_level.txt
t1ha-0.1.0.dist-info/RECORD
